README.rst
setup.py
pycnb/__init__.py
pycnb/core.py
pycnb/protocol.py
pycnb.egg-info/PKG-INFO
pycnb.egg-info/SOURCES.txt
pycnb.egg-info/dependency_links.txt
pycnb.egg-info/entry_points.txt
pycnb.egg-info/requires.txt
pycnb.egg-info/top_level.txt