Metadata-Version: 1.1
Name: pycnb
Version: 0.0.4
Summary: Library, CLI and Twisted protocol for `Czech National Bank daily rates
Home-page: https://github.com/yaccz/pycnb
Author: Jan Matejka
Author-email: yac@blesmrt.net
License: UNKNOWN
Platform: UNKNOWN
Classifier: Operating System :: POSIX
Classifier: License :: OSI Approved :: BSD License
Classifier: Programming Language :: Python
Classifier: Development Status :: 4 - Beta
Classifier: Framework :: Twisted
Classifier: Intended Audience :: End Users/Desktop
Classifier: Natural Language :: English
Classifier: Environment :: Console
Classifier: Topic :: Utilities
